simplepw/__init__.py
simplepw/main.py
simplepw/methods.py
simplepw-0.2.3.1.dist-info/METADATA
simplepw-0.2.3.1.dist-info/WHEEL
simplepw-0.2.3.1.dist-info/entry_points.txt
simplepw-0.2.3.1.dist-info/top_level.txt
simplepw-0.2.3.1.dist-info/RECORD
