Metadata-Version: 2.1
Name: simplepw
Version: 0.2.3.1
Summary: A CLI Application for generating and managing passwords
Author: pajhe
Author-email: piejeys@proton.me
Keywords: password generation
Requires-Dist: cryptography >=2.8
Requires-Dist: click
Requires-Dist: bcrypt
Requires-Dist: pathlib
Requires-Dist: sqlite3
